pklx/__init__.py
pklx/manage.py
pklx/objects.py
pklx/parser.py
pklx/settings.json
pklx/settings.py
pklx/tests.py
pklx/utils.py
pklx/visx/__init__.py
pklx/visx/backend.py
pklx/visx/static/android-chrome-192x192.png
pklx/visx/static/android-chrome-512x512.png
pklx/visx/static/apple-touch-icon.png
pklx/visx/static/favicon-16x16.png
pklx/visx/static/favicon-32x32.png
pklx/visx/static/favicon.ico
pklx/visx/static/index.css
pklx/visx/static/site.webmanifest
pklx/visx/static/visualisation.js
pklx/visx/templates/index.html
PKLX-0.0.5.dist-info/LICENSE
PKLX-0.0.5.dist-info/METADATA
PKLX-0.0.5.dist-info/WHEEL
PKLX-0.0.5.dist-info/entry_points.txt
PKLX-0.0.5.dist-info/top_level.txt
PKLX-0.0.5.dist-info/zip-safe
PKLX-0.0.5.dist-info/RECORD
