Metadata-Version: 2.1
Name: PKLX
Version: 0.0.5
Summary: PKLX
Author: PhylomatX
Author-email: phylomatx@gmail.com
Classifier: Programming Language :: Python :: 3
Classifier: License :: OSI Approved :: MIT License
Classifier: Operating System :: OS Independent
License-File: LICENSE
Requires-Dist: networkx ==3.1
Requires-Dist: flask ==2.3.2
